LICENSE
MANIFEST.in
README.rst
setup.py
django_ratings_underwave.egg-info/PKG-INFO
django_ratings_underwave.egg-info/SOURCES.txt
django_ratings_underwave.egg-info/dependency_links.txt
django_ratings_underwave.egg-info/requires.txt
django_ratings_underwave.egg-info/top_level.txt
djangoratings/__init__.py
djangoratings/admin.py
djangoratings/compat.py
djangoratings/default_settings.py
djangoratings/exceptions.py
djangoratings/fields.py
djangoratings/forms.py
djangoratings/managers.py
djangoratings/models.py
djangoratings/tests.py
djangoratings/views.py
djangoratings/management/__init__.py
djangoratings/management/commands/__init__.py
djangoratings/management/commands/update_recommendations.py
djangoratings/migrations/0001_initial.py
djangoratings/migrations/0002_use_GenericIPAddressField_instead_of_IPAddressField.py
djangoratings/migrations/__init__.py
djangoratings/templatetags/__init__.py
djangoratings/templatetags/ratings.py